pdaltagent/__init__.py
pdaltagent/config.py
pdaltagent/pd.py
pdaltagent/pdsend.py
pdaltagent/scripts/celeryd.defaults
pdaltagent/scripts/celeryd.service
pdaltagent/tasks.py
pdaltagent-0.1.0.dist-info/entry_points.txt
pdaltagent-0.1.0.dist-info/WHEEL
pdaltagent-0.1.0.dist-info/METADATA
pdaltagent-0.1.0.dist-info/RECORD
