Metadata-Version: 2.1
Name: pdaltagent
Version: 0.1.0
Summary: 
Author: Martin Stone
Author-email: martindstone@me.com
Requires-Python: >=3,<4
Classifier: Programming Language :: Python :: 3
Classifier: Programming Language :: Python :: 3.4
Classifier: Programming Language :: Python :: 3.5
Classifier: Programming Language :: Python :: 3.6
Classifier: Programming Language :: Python :: 3.7
Classifier: Programming Language :: Python :: 3.8
Requires-Dist: celery[redis] (>=4.4.2,<5.0.0)
Requires-Dist: requests (>=2.23.0,<3.0.0)
